teams_alerter/__init__.py
teams_alerter/core.py
teams_alerter/utils.py
tests/__init__.py
tests/test_core.py
teams_alerter-0.2.14.dist-info/METADATA
teams_alerter-0.2.14.dist-info/WHEEL
teams_alerter-0.2.14.dist-info/top_level.txt
teams_alerter-0.2.14.dist-info/RECORD
