Metadata-Version: 2.4
Name: teams-alerter
Version: 0.2.14
Summary: Module pour envoyer des alertes Teams via Pub/Sub
Author-email: Toki <t.bakotondrabe-ext@paris-turf.com>
License: MIT
Requires-Python: >=3.8
Requires-Dist: google-cloud-logging
Requires-Dist: google-cloud-pubsub
